termgrid/__init__.py
termgrid/grid.py
termgrid-0.0.1.dist-info/METADATA
termgrid-0.0.1.dist-info/WHEEL
termgrid-0.0.1.dist-info/top_level.txt
termgrid-0.0.1.dist-info/RECORD
