Metadata-Version: 2.1
Name: termgrid
Version: 0.0.1
Summary: Visualizing images and mathematical formulas in the command line
Author: Zhu Chongjing
Author-email: zhuchongjing_pypi@163.com
License: MIT
Classifier: Programming Language :: Python :: 3
Classifier: License :: OSI Approved :: MIT License
Classifier: Operating System :: OS Independent
